mcp_client_cli/__init__.py
mcp_client_cli/cli.py
mcp_client_cli/config.py
mcp_client_cli/const.py
mcp_client_cli/input.py
mcp_client_cli/memory.py
mcp_client_cli/output.py
mcp_client_cli/prompt.py
mcp_client_cli/storage.py
mcp_client_cli/tool.py
mcp_client_cli/testing/__init__.py
mcp_client_cli/testing/cli_integration.py
mcp_client_cli/testing/error_handler.py
mcp_client_cli/testing/issue_detector.py
mcp_client_cli/testing/issue_storage.py
mcp_client_cli/testing/mcp_tester.py
mcp_client_cli/testing/performance_tester.py
mcp_client_cli/testing/remediation.py
mcp_client_cli/testing/security_tester.py
mcp_client_cli/testing/test_storage.py
mcp_testing_framework-1.0.2.dist-info/licenses/LICENSE
mcp_testing_framework-1.0.2.dist-info/METADATA
mcp_testing_framework-1.0.2.dist-info/WHEEL
mcp_testing_framework-1.0.2.dist-info/entry_points.txt
mcp_testing_framework-1.0.2.dist-info/top_level.txt
mcp_testing_framework-1.0.2.dist-info/RECORD
