Metadata-Version: 2.4
Name: mcp-testing-framework
Version: 1.0.2
Summary: Comprehensive testing framework for Model Context Protocol (MCP) servers - Enhanced fork of mcp-client-cli with advanced testing capabilities
Author-email: Tosin Akinosho <tosin@decisioncrafters.com>
Maintainer-email: Tosin Akinosho <tosin@decisioncrafters.com>
License-Expression: MIT
Project-URL: Homepage, https://github.com/tosinakinosho/mcp-testing-framework
Project-URL: Documentation, https://mcp-testing-framework.readthedocs.io
Project-URL: Repository, https://github.com/tosinakinosho/mcp-testing-framework.git
Project-URL: Bug Tracker, https://github.com/tosinakinosho/mcp-testing-framework/issues
Project-URL: Changelog, https://github.com/tosinakinosho/mcp-testing-framework/blob/main/CHANGELOG.md
Project-URL: Original Project, https://github.com/original-author/mcp-client-cli
Keywords: mcp,testing,model-context-protocol,server-testing,automation,ci-cd,llm,ai-testing,integration-testing,performance-testing
Classifier: Development Status :: 4 - Beta
Classifier: Intended Audience :: Developers
Classifier: Programming Language :: Python :: 3
Classifier: Programming Language :: Python :: 3.10
Classifier: Programming Language :: Python :: 3.11
Classifier: Programming Language :: Python :: 3.12
Classifier: Topic :: Software Development :: Testing
Classifier: Topic :: Software Development :: Quality Assurance
Classifier: Topic :: Internet :: WWW/HTTP :: HTTP Servers
Classifier: Topic :: Scientific/Engineering :: Artificial Intelligence
Requires-Python: >=3.10
License-File: LICENSE
Requires-Dist: mcp>=1.0.0
Requires-Dist: anthropic>=0.40.0
Requires-Dist: openai>=1.54.0
Requires-Dist: pydantic>=2.0.0
Requires-Dist: click>=8.0.0
Requires-Dist: rich>=13.0.0
Requires-Dist: aiohttp>=3.8.0
Requires-Dist: asyncio-mqtt>=0.16.0
Requires-Dist: pytest>=7.0.0
Requires-Dist: pytest-asyncio>=0.21.0
Requires-Dist: pytest-timeout>=2.1.0
Requires-Dist: httpx>=0.24.0
Requires-Dist: websockets>=11.0.0
Requires-Dist: psutil>=5.9.0
Requires-Dist: memory-profiler>=0.60.0
Requires-Dist: py-spy>=0.3.14
Requires-Dist: jsonschema>=4.17.0
Requires-Dist: pyyaml>=6.0
Requires-Dist: toml>=0.10.2
Requires-Dist: jinja2>=3.1.0
Requires-Dist: tabulate>=0.9.0
Requires-Dist: colorama>=0.4.6
Requires-Dist: tqdm>=4.64.0
Requires-Dist: anyio>=3.6.0
Requires-Dist: langchain-core>=0.1.0
Requires-Dist: langchain>=0.1.0
Requires-Dist: langgraph>=0.1.0
Requires-Dist: aiosqlite>=0.17.0
Requires-Dist: jsonschema-pydantic>=0.1.0
Requires-Dist: commentjson>=0.9.0
Provides-Extra: dev
Requires-Dist: pytest>=7.0.0; extra == "dev"
Requires-Dist: pytest-cov>=4.0.0; extra == "dev"
Requires-Dist: pytest-asyncio>=0.21.0; extra == "dev"
Requires-Dist: black>=23.0.0; extra == "dev"
Requires-Dist: isort>=5.12.0; extra == "dev"
Requires-Dist: flake8>=6.0.0; extra == "dev"
Requires-Dist: mypy>=1.0.0; extra == "dev"
Requires-Dist: pre-commit>=3.0.0; extra == "dev"
Provides-Extra: docs
Requires-Dist: mkdocs>=1.4.0; extra == "docs"
Requires-Dist: mkdocs-material>=9.0.0; extra == "docs"
Requires-Dist: mkdocstrings[python]>=0.20.0; extra == "docs"
Provides-Extra: security
Requires-Dist: bandit>=1.7.0; extra == "security"
Requires-Dist: safety>=2.3.0; extra == "security"
Requires-Dist: semgrep>=1.0.0; extra == "security"
Dynamic: license-file
